{
  "generatedAt": "2026-07-02",
  "currentTotal": 1004,
  "target": "1000+ active copy-paste SKILL.md files",
  "phaseComplete": [
    "Audited existing 284 skills for real-world usefulness.",
    "Added original premium expansion packs to reach 1000+ active skills.",
    "Reorganized browse taxonomy around real-world outcomes."
  ],
  "nextExpansionBacklog": [
    {
      "group": "Creator Command Center",
      "additionalSkills": 120,
      "examples": [
        "podcast operations",
        "brand deals",
        "AI avatar production",
        "community moderation"
      ]
    },
    {
      "group": "Business & Revenue",
      "additionalSkills": 140,
      "examples": [
        "agency delivery",
        "client reporting",
        "procurement",
        "franchise/local business"
      ]
    },
    {
      "group": "Product, Developer & Research",
      "additionalSkills": 160,
      "examples": [
        "QA automation prompts",
        "architecture reviews",
        "academic research",
        "prompt evals"
      ]
    },
    {
      "group": "Documents, Data & Decisions",
      "additionalSkills": 100,
      "examples": [
        "board decks",
        "financial models",
        "survey dashboards",
        "grant writing"
      ]
    },
    {
      "group": "Live Connectors & Automations",
      "additionalSkills": 180,
      "examples": [
        "Make/n8n playbooks",
        "CRM automations",
        "analytics digests",
        "support escalations"
      ]
    }
  ],
  "sourcePolicy": "Do not copy third-party skills. Use public repos only for category demand signals, then write original X Freeze workflows from scratch."
}
